metaflow_magicdir/__init__.py
metaflow_magicdir/_nbdev.py
metaflow_magicdir/md.py
metaflow_magicdir-0.0.4.dist-info/LICENSE
metaflow_magicdir-0.0.4.dist-info/METADATA
metaflow_magicdir-0.0.4.dist-info/WHEEL
metaflow_magicdir-0.0.4.dist-info/entry_points.txt
metaflow_magicdir-0.0.4.dist-info/top_level.txt
metaflow_magicdir-0.0.4.dist-info/RECORD
