Metadata-Version: 2.1
Name: metaflow-magicdir
Version: 0.0.4
Summary: "Save Entire Directories Into Metaflow's Metadata Store"
Home-page: https://github.com/Outerbounds/metaflow_magicdir/tree/master/
Author: Hamel Husain
Author-email: hamel@outerbounds.co
License: Apache Software License 2.0
Keywords: metaflow machine-learning
Platform: UNKNOWN
Classifier: Development Status :: 3 - Alpha
Classifier: Intended Audience :: Developers
Classifier: Natural Language :: English
Classifier: Programming Language :: Python :: 3.6
Classifier: Programming Language :: Python :: 3.7
Classifier: Programming Language :: Python :: 3.8
Classifier: Programming Language :: Python :: 3.9
Classifier: Programming Language :: Python :: 3.10
Classifier: License :: OSI Approved :: Apache Software License
Requires-Python: >=3.6
License-File: LICENSE
Requires-Dist: pip
Requires-Dist: packaging
Requires-Dist: metaflow
Provides-Extra: dev
